[
  {
    "schemaVersion": "https://movielabs.com/omc/json/schema/v2.6",
    "entityType": "Character",
    "identifier": [
      {
        "identifierScope": "labkoat",
        "identifierValue": "chr/ya1HLUS2xbRpDf2JYQ-wv"
      }
    ],
    "name": "Keira",
    "Context": [
      {
        "schemaVersion": "https://movielabs.com/omc/json/schema/v2.6",
        "entityType": "Context",
        "identifier": [
          {
            "identifierScope": "labkoat",
            "identifierValue": "cxt/Y4xT3kqb60guubgFC_-hz-1-1"
          }
        ],
        "contextType": "narrative",
        "featuresIn": {
          "NarrativeScene": [
            {
              "schemaVersion": "https://movielabs.com/omc/json/schema/v2.6",
              "entityType": "NarrativeScene",
              "identifier": [
                {
                  "identifierScope": "labkoat",
                  "identifierValue": "nscn/St_Hh-LxAQo4ICUAtbZ0v"
                }
              ],
              "name": "Space",
              "description": null,
              "sceneNumber": "2",
              "Context": [
                {
                  "schemaVersion": "https://movielabs.com/omc/json/schema/v2.6",
                  "entityType": "Context",
                  "identifier": [
                    {
                      "identifierScope": "labkoat",
                      "identifierValue": "cxt/PyF91eYzluPFglSRgiOdz-1-1"
                    }
                  ],
                  "features": {
                    "NarrativeObject": null
                  }
                },
                {
                  "schemaVersion": "https://movielabs.com/omc/json/schema/v2.6",
                  "entityType": "Context",
                  "identifier": [
                    {
                      "identifierScope": "labkoat",
                      "identifierValue": "cxt/PyF91eYzluPFglSRgiOdz-2-2"
                    }
                  ],
                  "features": {
                    "NarrativeObject": null
                  }
                },
                {
                  "schemaVersion": "https://movielabs.com/omc/json/schema/v2.6",
                  "entityType": "Context",
                  "identifier": [
                    {
                      "identifierScope": "labkoat",
                      "identifierValue": "cxt/PyF91eYzluPFglSRgiOdz-3-3"
                    }
                  ],
                  "features": {
                    "NarrativeObject": null
                  }
                },
                {
                  "schemaVersion": "https://movielabs.com/omc/json/schema/v2.6",
                  "entityType": "Context",
                  "identifier": [
                    {
                      "identifierScope": "labkoat",
                      "identifierValue": "cxt/PyF91eYzluPFglSRgiOdz-4-4"
                    }
                  ],
                  "features": {
                    "NarrativeObject": null
                  }
                },
                {
                  "schemaVersion": "https://movielabs.com/omc/json/schema/v2.6",
                  "entityType": "Context",
                  "identifier": [
                    {
                      "identifierScope": "labkoat",
                      "identifierValue": "cxt/PyF91eYzluPFglSRgiOdz-5-5"
                    }
                  ],
                  "features": null
                },
                {
                  "schemaVersion": "https://movielabs.com/omc/json/schema/v2.6",
                  "entityType": "Context",
                  "identifier": [
                    {
                      "identifierScope": "labkoat",
                      "identifierValue": "cxt/PyF91eYzluPFglSRgiOdz-6-6"
                    }
                  ],
                  "features": null
                },
                {
                  "schemaVersion": "https://movielabs.com/omc/json/schema/v2.6",
                  "entityType": "Context",
                  "identifier": [
                    {
                      "identifierScope": "labkoat",
                      "identifierValue": "cxt/PyF91eYzluPFglSRgiOdz-7-7"
                    }
                  ],
                  "features": null
                }
              ]
            },
            {
              "schemaVersion": "https://movielabs.com/omc/json/schema/v2.6",
              "entityType": "NarrativeScene",
              "identifier": [
                {
                  "identifierScope": "labkoat",
                  "identifierValue": "nscn/lmPkGo1nXjJgfeNnoxArq"
                }
              ],
              "name": "Beach",
              "description": null,
              "sceneNumber": "5",
              "Context": [
                {
                  "schemaVersion": "https://movielabs.com/omc/json/schema/v2.6",
                  "entityType": "Context",
                  "identifier": [
                    {
                      "identifierScope": "labkoat",
                      "identifierValue": "cxt/qywm_qU78IVRhQtagirto-1-1"
                    }
                  ],
                  "features": {
                    "NarrativeObject": null
                  }
                },
                {
                  "schemaVersion": "https://movielabs.com/omc/json/schema/v2.6",
                  "entityType": "Context",
                  "identifier": [
                    {
                      "identifierScope": "labkoat",
                      "identifierValue": "cxt/qywm_qU78IVRhQtagirto-2-2"
                    }
                  ],
                  "features": {
                    "NarrativeObject": null
                  }
                },
                {
                  "schemaVersion": "https://movielabs.com/omc/json/schema/v2.6",
                  "entityType": "Context",
                  "identifier": [
                    {
                      "identifierScope": "labkoat",
                      "identifierValue": "cxt/qywm_qU78IVRhQtagirto-3-3"
                    }
                  ],
                  "features": {
                    "NarrativeObject": null
                  }
                },
                {
                  "schemaVersion": "https://movielabs.com/omc/json/schema/v2.6",
                  "entityType": "Context",
                  "identifier": [
                    {
                      "identifierScope": "labkoat",
                      "identifierValue": "cxt/qywm_qU78IVRhQtagirto-4-4"
                    }
                  ],
                  "features": {
                    "NarrativeObject": null
                  }
                },
                {
                  "schemaVersion": "https://movielabs.com/omc/json/schema/v2.6",
                  "entityType": "Context",
                  "identifier": [
                    {
                      "identifierScope": "labkoat",
                      "identifierValue": "cxt/qywm_qU78IVRhQtagirto-5-5"
                    }
                  ],
                  "features": {
                    "NarrativeObject": null
                  }
                },
                {
                  "schemaVersion": "https://movielabs.com/omc/json/schema/v2.6",
                  "entityType": "Context",
                  "identifier": [
                    {
                      "identifierScope": "labkoat",
                      "identifierValue": "cxt/qywm_qU78IVRhQtagirto-7-7"
                    }
                  ],
                  "features": null
                },
                {
                  "schemaVersion": "https://movielabs.com/omc/json/schema/v2.6",
                  "entityType": "Context",
                  "identifier": [
                    {
                      "identifierScope": "labkoat",
                      "identifierValue": "cxt/qywm_qU78IVRhQtagirto-8-8"
                    }
                  ],
                  "features": null
                }
              ]
            },
            {
              "schemaVersion": "https://movielabs.com/omc/json/schema/v2.6",
              "entityType": "NarrativeScene",
              "identifier": [
                {
                  "identifierScope": "labkoat",
                  "identifierValue": "nscn/1icPnKZ4LRliFd3WI9urA"
                }
              ],
              "name": "Plateau",
              "description": null,
              "sceneNumber": "7",
              "Context": [
                {
                  "schemaVersion": "https://movielabs.com/omc/json/schema/v2.6",
                  "entityType": "Context",
                  "identifier": [
                    {
                      "identifierScope": "labkoat",
                      "identifierValue": "cxt/xoZa6T_BuGYgHM8Q0rqQt-1-1"
                    }
                  ],
                  "features": {
                    "NarrativeObject": null
                  }
                },
                {
                  "schemaVersion": "https://movielabs.com/omc/json/schema/v2.6",
                  "entityType": "Context",
                  "identifier": [
                    {
                      "identifierScope": "labkoat",
                      "identifierValue": "cxt/xoZa6T_BuGYgHM8Q0rqQt-2-2"
                    }
                  ],
                  "features": {
                    "NarrativeObject": null
                  }
                },
                {
                  "schemaVersion": "https://movielabs.com/omc/json/schema/v2.6",
                  "entityType": "Context",
                  "identifier": [
                    {
                      "identifierScope": "labkoat",
                      "identifierValue": "cxt/xoZa6T_BuGYgHM8Q0rqQt-3-3"
                    }
                  ],
                  "features": {
                    "NarrativeObject": null
                  }
                },
                {
                  "schemaVersion": "https://movielabs.com/omc/json/schema/v2.6",
                  "entityType": "Context",
                  "identifier": [
                    {
                      "identifierScope": "labkoat",
                      "identifierValue": "cxt/xoZa6T_BuGYgHM8Q0rqQt-4-4"
                    }
                  ],
                  "features": {
                    "NarrativeObject": null
                  }
                },
                {
                  "schemaVersion": "https://movielabs.com/omc/json/schema/v2.6",
                  "entityType": "Context",
                  "identifier": [
                    {
                      "identifierScope": "labkoat",
                      "identifierValue": "cxt/xoZa6T_BuGYgHM8Q0rqQt-5-5"
                    }
                  ],
                  "features": {
                    "NarrativeObject": null
                  }
                },
                {
                  "schemaVersion": "https://movielabs.com/omc/json/schema/v2.6",
                  "entityType": "Context",
                  "identifier": [
                    {
                      "identifierScope": "labkoat",
                      "identifierValue": "cxt/xoZa6T_BuGYgHM8Q0rqQt-6-6"
                    }
                  ],
                  "features": {
                    "NarrativeObject": null
                  }
                },
                {
                  "schemaVersion": "https://movielabs.com/omc/json/schema/v2.6",
                  "entityType": "Context",
                  "identifier": [
                    {
                      "identifierScope": "labkoat",
                      "identifierValue": "cxt/xoZa6T_BuGYgHM8Q0rqQt-7-7"
                    }
                  ],
                  "features": {
                    "NarrativeObject": null
                  }
                },
                {
                  "schemaVersion": "https://movielabs.com/omc/json/schema/v2.6",
                  "entityType": "Context",
                  "identifier": [
                    {
                      "identifierScope": "labkoat",
                      "identifierValue": "cxt/xoZa6T_BuGYgHM8Q0rqQt-9-9"
                    }
                  ],
                  "features": null
                },
                {
                  "schemaVersion": "https://movielabs.com/omc/json/schema/v2.6",
                  "entityType": "Context",
                  "identifier": [
                    {
                      "identifierScope": "labkoat",
                      "identifierValue": "cxt/xoZa6T_BuGYgHM8Q0rqQt-10-10"
                    }
                  ],
                  "features": null
                }
              ]
            }
          ]
        },
        "needs": null,
        "has": null
      },
      {
        "schemaVersion": "https://movielabs.com/omc/json/schema/v2.6",
        "entityType": "Context",
        "identifier": [
          {
            "identifierScope": "labkoat",
            "identifierValue": "cxt/Y4xT3kqb60guubgFC_-hz-2-2"
          }
        ],
        "contextType": "concept",
        "featuresIn": null,
        "needs": null,
        "has": {
          "Asset": [
            {
              "schemaVersion": "https://movielabs.com/omc/json/schema/v2.6",
              "entityType": "Asset",
              "identifier": [
                {
                  "identifierScope": "labkoat",
                  "identifierValue": "asgp/9GCqyscubejmGi3o9Uv6H"
                }
              ],
              "name": "Concept Art for Kiera"
            }
          ]
        }
      }
    ]
  },
  {
    "schemaVersion": "https://movielabs.com/omc/json/schema/v2.6",
    "entityType": "Character",
    "identifier": [
      {
        "identifierScope": "labkoat",
        "identifierValue": "chr/O5vdheU9idw0DhwDrjoty"
      }
    ],
    "name": "Trilobot",
    "Context": [
      {
        "schemaVersion": "https://movielabs.com/omc/json/schema/v2.6",
        "entityType": "Context",
        "identifier": [
          {
            "identifierScope": "labkoat",
            "identifierValue": "cxt/Ki6uaGlM82HGRlBgEnMXe-1-1"
          }
        ],
        "contextType": "narrative",
        "featuresIn": {
          "NarrativeScene": [
            {
              "schemaVersion": "https://movielabs.com/omc/json/schema/v2.6",
              "entityType": "NarrativeScene",
              "identifier": [
                {
                  "identifierScope": "labkoat",
                  "identifierValue": "nscn/wz_MHOLYI3VwYx_0AX47Y"
                }
              ],
              "name": "Title",
              "description": null,
              "sceneNumber": "1",
              "Context": [
                {
                  "schemaVersion": "https://movielabs.com/omc/json/schema/v2.6",
                  "entityType": "Context",
                  "identifier": [
                    {
                      "identifierScope": "labkoat",
                      "identifierValue": "cxt/Yhk9Nqa9UvkoOmccdPEJf-1-1"
                    }
                  ],
                  "features": {
                    "NarrativeObject": null
                  }
                },
                {
                  "schemaVersion": "https://movielabs.com/omc/json/schema/v2.6",
                  "entityType": "Context",
                  "identifier": [
                    {
                      "identifierScope": "labkoat",
                      "identifierValue": "cxt/Yhk9Nqa9UvkoOmccdPEJf-2-2"
                    }
                  ],
                  "features": {
                    "NarrativeObject": null
                  }
                },
                {
                  "schemaVersion": "https://movielabs.com/omc/json/schema/v2.6",
                  "entityType": "Context",
                  "identifier": [
                    {
                      "identifierScope": "labkoat",
                      "identifierValue": "cxt/Yhk9Nqa9UvkoOmccdPEJf-3-3"
                    }
                  ],
                  "features": {
                    "NarrativeObject": null
                  }
                },
                {
                  "schemaVersion": "https://movielabs.com/omc/json/schema/v2.6",
                  "entityType": "Context",
                  "identifier": [
                    {
                      "identifierScope": "labkoat",
                      "identifierValue": "cxt/Yhk9Nqa9UvkoOmccdPEJf-4-4"
                    }
                  ],
                  "features": {
                    "NarrativeObject": null
                  }
                },
                {
                  "schemaVersion": "https://movielabs.com/omc/json/schema/v2.6",
                  "entityType": "Context",
                  "identifier": [
                    {
                      "identifierScope": "labkoat",
                      "identifierValue": "cxt/Yhk9Nqa9UvkoOmccdPEJf-5-5"
                    }
                  ],
                  "features": null
                },
                {
                  "schemaVersion": "https://movielabs.com/omc/json/schema/v2.6",
                  "entityType": "Context",
                  "identifier": [
                    {
                      "identifierScope": "labkoat",
                      "identifierValue": "cxt/Yhk9Nqa9UvkoOmccdPEJf-6-6"
                    }
                  ],
                  "features": null
                },
                {
                  "schemaVersion": "https://movielabs.com/omc/json/schema/v2.6",
                  "entityType": "Context",
                  "identifier": [
                    {
                      "identifierScope": "labkoat",
                      "identifierValue": "cxt/Yhk9Nqa9UvkoOmccdPEJf-7-7"
                    }
                  ],
                  "features": null
                }
              ]
            },
            {
              "schemaVersion": "https://movielabs.com/omc/json/schema/v2.6",
              "entityType": "NarrativeScene",
              "identifier": [
                {
                  "identifierScope": "labkoat",
                  "identifierValue": "nscn/xJpXtpM0G2QQM92TITfTf"
                }
              ],
              "name": "Space - Moments Later",
              "description": null,
              "sceneNumber": "3",
              "Context": [
                {
                  "schemaVersion": "https://movielabs.com/omc/json/schema/v2.6",
                  "entityType": "Context",
                  "identifier": [
                    {
                      "identifierScope": "labkoat",
                      "identifierValue": "cxt/dewQzS8jVOgaWkIOSIEwd-1-1"
                    }
                  ],
                  "features": {
                    "NarrativeObject": null
                  }
                },
                {
                  "schemaVersion": "https://movielabs.com/omc/json/schema/v2.6",
                  "entityType": "Context",
                  "identifier": [
                    {
                      "identifierScope": "labkoat",
                      "identifierValue": "cxt/dewQzS8jVOgaWkIOSIEwd-2-2"
                    }
                  ],
                  "features": {
                    "NarrativeObject": null
                  }
                },
                {
                  "schemaVersion": "https://movielabs.com/omc/json/schema/v2.6",
                  "entityType": "Context",
                  "identifier": [
                    {
                      "identifierScope": "labkoat",
                      "identifierValue": "cxt/dewQzS8jVOgaWkIOSIEwd-3-3"
                    }
                  ],
                  "features": {
                    "NarrativeObject": null
                  }
                },
                {
                  "schemaVersion": "https://movielabs.com/omc/json/schema/v2.6",
                  "entityType": "Context",
                  "identifier": [
                    {
                      "identifierScope": "labkoat",
                      "identifierValue": "cxt/dewQzS8jVOgaWkIOSIEwd-4-4"
                    }
                  ],
                  "features": {
                    "NarrativeObject": null
                  }
                },
                {
                  "schemaVersion": "https://movielabs.com/omc/json/schema/v2.6",
                  "entityType": "Context",
                  "identifier": [
                    {
                      "identifierScope": "labkoat",
                      "identifierValue": "cxt/dewQzS8jVOgaWkIOSIEwd-5-5"
                    }
                  ],
                  "features": null
                },
                {
                  "schemaVersion": "https://movielabs.com/omc/json/schema/v2.6",
                  "entityType": "Context",
                  "identifier": [
                    {
                      "identifierScope": "labkoat",
                      "identifierValue": "cxt/dewQzS8jVOgaWkIOSIEwd-6-6"
                    }
                  ],
                  "features": null
                }
              ]
            },
            {
              "schemaVersion": "https://movielabs.com/omc/json/schema/v2.6",
              "entityType": "NarrativeScene",
              "identifier": [
                {
                  "identifierScope": "labkoat",
                  "identifierValue": "nscn/3EF7fR-xOJ7IamLr2iYsg"
                }
              ],
              "name": "Atmosphere",
              "description": null,
              "sceneNumber": "4",
              "Context": [
                {
                  "schemaVersion": "https://movielabs.com/omc/json/schema/v2.6",
                  "entityType": "Context",
                  "identifier": [
                    {
                      "identifierScope": "labkoat",
                      "identifierValue": "cxt/02GT3AlA1wywIJLDIAuUl-1-1"
                    }
                  ],
                  "features": {
                    "NarrativeObject": null
                  }
                },
                {
                  "schemaVersion": "https://movielabs.com/omc/json/schema/v2.6",
                  "entityType": "Context",
                  "identifier": [
                    {
                      "identifierScope": "labkoat",
                      "identifierValue": "cxt/02GT3AlA1wywIJLDIAuUl-2-2"
                    }
                  ],
                  "features": {
                    "NarrativeObject": null
                  }
                },
                {
                  "schemaVersion": "https://movielabs.com/omc/json/schema/v2.6",
                  "entityType": "Context",
                  "identifier": [
                    {
                      "identifierScope": "labkoat",
                      "identifierValue": "cxt/02GT3AlA1wywIJLDIAuUl-3-3"
                    }
                  ],
                  "features": {
                    "NarrativeObject": null
                  }
                },
                {
                  "schemaVersion": "https://movielabs.com/omc/json/schema/v2.6",
                  "entityType": "Context",
                  "identifier": [
                    {
                      "identifierScope": "labkoat",
                      "identifierValue": "cxt/02GT3AlA1wywIJLDIAuUl-4-4"
                    }
                  ],
                  "features": {
                    "NarrativeObject": null
                  }
                },
                {
                  "schemaVersion": "https://movielabs.com/omc/json/schema/v2.6",
                  "entityType": "Context",
                  "identifier": [
                    {
                      "identifierScope": "labkoat",
                      "identifierValue": "cxt/02GT3AlA1wywIJLDIAuUl-6-6"
                    }
                  ],
                  "features": null
                },
                {
                  "schemaVersion": "https://movielabs.com/omc/json/schema/v2.6",
                  "entityType": "Context",
                  "identifier": [
                    {
                      "identifierScope": "labkoat",
                      "identifierValue": "cxt/02GT3AlA1wywIJLDIAuUl-7-7"
                    }
                  ],
                  "features": null
                }
              ]
            },
            {
              "schemaVersion": "https://movielabs.com/omc/json/schema/v2.6",
              "entityType": "NarrativeScene",
              "identifier": [
                {
                  "identifierScope": "labkoat",
                  "identifierValue": "nscn/lmPkGo1nXjJgfeNnoxArq"
                }
              ],
              "name": "Beach",
              "description": null,
              "sceneNumber": "5",
              "Context": [
                {
                  "schemaVersion": "https://movielabs.com/omc/json/schema/v2.6",
                  "entityType": "Context",
                  "identifier": [
                    {
                      "identifierScope": "labkoat",
                      "identifierValue": "cxt/qywm_qU78IVRhQtagirto-1-1"
                    }
                  ],
                  "features": {
                    "NarrativeObject": null
                  }
                },
                {
                  "schemaVersion": "https://movielabs.com/omc/json/schema/v2.6",
                  "entityType": "Context",
                  "identifier": [
                    {
                      "identifierScope": "labkoat",
                      "identifierValue": "cxt/qywm_qU78IVRhQtagirto-2-2"
                    }
                  ],
                  "features": {
                    "NarrativeObject": null
                  }
                },
                {
                  "schemaVersion": "https://movielabs.com/omc/json/schema/v2.6",
                  "entityType": "Context",
                  "identifier": [
                    {
                      "identifierScope": "labkoat",
                      "identifierValue": "cxt/qywm_qU78IVRhQtagirto-3-3"
                    }
                  ],
                  "features": {
                    "NarrativeObject": null
                  }
                },
                {
                  "schemaVersion": "https://movielabs.com/omc/json/schema/v2.6",
                  "entityType": "Context",
                  "identifier": [
                    {
                      "identifierScope": "labkoat",
                      "identifierValue": "cxt/qywm_qU78IVRhQtagirto-4-4"
                    }
                  ],
                  "features": {
                    "NarrativeObject": null
                  }
                },
                {
                  "schemaVersion": "https://movielabs.com/omc/json/schema/v2.6",
                  "entityType": "Context",
                  "identifier": [
                    {
                      "identifierScope": "labkoat",
                      "identifierValue": "cxt/qywm_qU78IVRhQtagirto-5-5"
                    }
                  ],
                  "features": {
                    "NarrativeObject": null
                  }
                },
                {
                  "schemaVersion": "https://movielabs.com/omc/json/schema/v2.6",
                  "entityType": "Context",
                  "identifier": [
                    {
                      "identifierScope": "labkoat",
                      "identifierValue": "cxt/qywm_qU78IVRhQtagirto-7-7"
                    }
                  ],
                  "features": null
                },
                {
                  "schemaVersion": "https://movielabs.com/omc/json/schema/v2.6",
                  "entityType": "Context",
                  "identifier": [
                    {
                      "identifierScope": "labkoat",
                      "identifierValue": "cxt/qywm_qU78IVRhQtagirto-8-8"
                    }
                  ],
                  "features": null
                }
              ]
            },
            {
              "schemaVersion": "https://movielabs.com/omc/json/schema/v2.6",
              "entityType": "NarrativeScene",
              "identifier": [
                {
                  "identifierScope": "labkoat",
                  "identifierValue": "nscn/zH9BzX8cjf-wY6N-HE6fg"
                }
              ],
              "name": "Jungle",
              "description": null,
              "sceneNumber": "6",
              "Context": [
                {
                  "schemaVersion": "https://movielabs.com/omc/json/schema/v2.6",
                  "entityType": "Context",
                  "identifier": [
                    {
                      "identifierScope": "labkoat",
                      "identifierValue": "cxt/G2_QEXSZYS32wc3Z0Ecdx-1-1"
                    }
                  ],
                  "features": {
                    "NarrativeObject": null
                  }
                },
                {
                  "schemaVersion": "https://movielabs.com/omc/json/schema/v2.6",
                  "entityType": "Context",
                  "identifier": [
                    {
                      "identifierScope": "labkoat",
                      "identifierValue": "cxt/G2_QEXSZYS32wc3Z0Ecdx-2-2"
                    }
                  ],
                  "features": {
                    "NarrativeObject": null
                  }
                },
                {
                  "schemaVersion": "https://movielabs.com/omc/json/schema/v2.6",
                  "entityType": "Context",
                  "identifier": [
                    {
                      "identifierScope": "labkoat",
                      "identifierValue": "cxt/G2_QEXSZYS32wc3Z0Ecdx-3-3"
                    }
                  ],
                  "features": {
                    "NarrativeObject": null
                  }
                },
                {
                  "schemaVersion": "https://movielabs.com/omc/json/schema/v2.6",
                  "entityType": "Context",
                  "identifier": [
                    {
                      "identifierScope": "labkoat",
                      "identifierValue": "cxt/G2_QEXSZYS32wc3Z0Ecdx-4-4"
                    }
                  ],
                  "features": {
                    "NarrativeObject": null
                  }
                },
                {
                  "schemaVersion": "https://movielabs.com/omc/json/schema/v2.6",
                  "entityType": "Context",
                  "identifier": [
                    {
                      "identifierScope": "labkoat",
                      "identifierValue": "cxt/G2_QEXSZYS32wc3Z0Ecdx-6-6"
                    }
                  ],
                  "features": null
                },
                {
                  "schemaVersion": "https://movielabs.com/omc/json/schema/v2.6",
                  "entityType": "Context",
                  "identifier": [
                    {
                      "identifierScope": "labkoat",
                      "identifierValue": "cxt/G2_QEXSZYS32wc3Z0Ecdx-7-7"
                    }
                  ],
                  "features": null
                }
              ]
            },
            {
              "schemaVersion": "https://movielabs.com/omc/json/schema/v2.6",
              "entityType": "NarrativeScene",
              "identifier": [
                {
                  "identifierScope": "labkoat",
                  "identifierValue": "nscn/1icPnKZ4LRliFd3WI9urA"
                }
              ],
              "name": "Plateau",
              "description": null,
              "sceneNumber": "7",
              "Context": [
                {
                  "schemaVersion": "https://movielabs.com/omc/json/schema/v2.6",
                  "entityType": "Context",
                  "identifier": [
                    {
                      "identifierScope": "labkoat",
                      "identifierValue": "cxt/xoZa6T_BuGYgHM8Q0rqQt-1-1"
                    }
                  ],
                  "features": {
                    "NarrativeObject": null
                  }
                },
                {
                  "schemaVersion": "https://movielabs.com/omc/json/schema/v2.6",
                  "entityType": "Context",
                  "identifier": [
                    {
                      "identifierScope": "labkoat",
                      "identifierValue": "cxt/xoZa6T_BuGYgHM8Q0rqQt-2-2"
                    }
                  ],
                  "features": {
                    "NarrativeObject": null
                  }
                },
                {
                  "schemaVersion": "https://movielabs.com/omc/json/schema/v2.6",
                  "entityType": "Context",
                  "identifier": [
                    {
                      "identifierScope": "labkoat",
                      "identifierValue": "cxt/xoZa6T_BuGYgHM8Q0rqQt-3-3"
                    }
                  ],
                  "features": {
                    "NarrativeObject": null
                  }
                },
                {
                  "schemaVersion": "https://movielabs.com/omc/json/schema/v2.6",
                  "entityType": "Context",
                  "identifier": [
                    {
                      "identifierScope": "labkoat",
                      "identifierValue": "cxt/xoZa6T_BuGYgHM8Q0rqQt-4-4"
                    }
                  ],
                  "features": {
                    "NarrativeObject": null
                  }
                },
                {
                  "schemaVersion": "https://movielabs.com/omc/json/schema/v2.6",
                  "entityType": "Context",
                  "identifier": [
                    {
                      "identifierScope": "labkoat",
                      "identifierValue": "cxt/xoZa6T_BuGYgHM8Q0rqQt-5-5"
                    }
                  ],
                  "features": {
                    "NarrativeObject": null
                  }
                },
                {
                  "schemaVersion": "https://movielabs.com/omc/json/schema/v2.6",
                  "entityType": "Context",
                  "identifier": [
                    {
                      "identifierScope": "labkoat",
                      "identifierValue": "cxt/xoZa6T_BuGYgHM8Q0rqQt-6-6"
                    }
                  ],
                  "features": {
                    "NarrativeObject": null
                  }
                },
                {
                  "schemaVersion": "https://movielabs.com/omc/json/schema/v2.6",
                  "entityType": "Context",
                  "identifier": [
                    {
                      "identifierScope": "labkoat",
                      "identifierValue": "cxt/xoZa6T_BuGYgHM8Q0rqQt-7-7"
                    }
                  ],
                  "features": {
                    "NarrativeObject": null
                  }
                },
                {
                  "schemaVersion": "https://movielabs.com/omc/json/schema/v2.6",
                  "entityType": "Context",
                  "identifier": [
                    {
                      "identifierScope": "labkoat",
                      "identifierValue": "cxt/xoZa6T_BuGYgHM8Q0rqQt-9-9"
                    }
                  ],
                  "features": null
                },
                {
                  "schemaVersion": "https://movielabs.com/omc/json/schema/v2.6",
                  "entityType": "Context",
                  "identifier": [
                    {
                      "identifierScope": "labkoat",
                      "identifierValue": "cxt/xoZa6T_BuGYgHM8Q0rqQt-10-10"
                    }
                  ],
                  "features": null
                }
              ]
            }
          ]
        },
        "needs": {
          "NarrativeObject": [
            {
              "schemaVersion": "https://movielabs.com/omc/json/schema/v2.6",
              "entityType": "NarrativeObject",
              "identifier": [
                {
                  "identifierScope": "labkoat",
                  "identifierValue": "nprp/ozmg19-jNdhIlO1HwVP5G"
                }
              ],
              "name": "Satellites hatch",
              "description": "The hatch Sven removes to fix the satellite.",
              "narrativeType": "narrativeProp"
            },
            {
              "schemaVersion": "https://movielabs.com/omc/json/schema/v2.6",
              "entityType": "NarrativeObject",
              "identifier": [
                {
                  "identifierScope": "labkoat",
                  "identifierValue": "nprp/aAZTJ26A0mCCLosGQ3Ryg"
                }
              ],
              "name": "Windshield",
              "description": "The windshield of Sven's ship.",
              "narrativeType": "narrativeProp"
            },
            {
              "schemaVersion": "https://movielabs.com/omc/json/schema/v2.6",
              "entityType": "NarrativeObject",
              "identifier": [
                {
                  "identifierScope": "labkoat",
                  "identifierValue": "nprp/5is74zVxCRl5hipIHfMzB"
                }
              ],
              "name": "Satellite",
              "description": "The Gromet-12 plantetary observation satellite finds planets that are habitable for humans",
              "narrativeType": "narrativeProp"
            },
            {
              "schemaVersion": "https://movielabs.com/omc/json/schema/v2.6",
              "entityType": "NarrativeObject",
              "identifier": [
                {
                  "identifierScope": "labkoat",
                  "identifierValue": "nprp/eM2Njo6EK-OEIzEL9xDlr"
                }
              ],
              "name": "Fruit cluster",
              "description": "The cluster of fruit Sven sets off to kill the Trilobot",
              "narrativeType": "narrativeProp"
            },
            {
              "schemaVersion": "https://movielabs.com/omc/json/schema/v2.6",
              "entityType": "NarrativeObject",
              "identifier": [
                {
                  "identifierScope": "labkoat",
                  "identifierValue": "nprp/BtBYAFQ_Moo4PQlqSztGz"
                }
              ],
              "name": "Rock - Beach",
              "description": "The rock on the beach that Sven hides behind.",
              "narrativeType": "narrativeProp"
            },
            {
              "schemaVersion": "https://movielabs.com/omc/json/schema/v2.6",
              "entityType": "NarrativeObject",
              "identifier": [
                {
                  "identifierScope": "labkoat",
                  "identifierValue": "nprp/ryhQTqM7Dpo0fe-9PJhQh"
                }
              ],
              "name": "Spaceship",
              "description": "Sven's Lancelot-12 galaxy cruiser which is the pick up truck of space vehicles",
              "narrativeType": "narrativeVehicle"
            },
            {
              "schemaVersion": "https://movielabs.com/omc/json/schema/v2.6",
              "entityType": "NarrativeObject",
              "identifier": [
                {
                  "identifierScope": "labkoat",
                  "identifierValue": "nprp/HL9EpbbzFK320fweoiFsM"
                }
              ],
              "name": "Ground",
              "description": "The terrain that Sven runs on in the Jungle and Plateau",
              "narrativeType": "narrativeGreenery"
            },
            {
              "schemaVersion": "https://movielabs.com/omc/json/schema/v2.6",
              "entityType": "NarrativeObject",
              "identifier": [
                {
                  "identifierScope": "labkoat",
                  "identifierValue": "nprp/OAjeFuQtL5Au4DHJMu6Uz"
                }
              ],
              "name": "Canopy",
              "description": "The canopy that Svens breaks through as he runs through the jungle.",
              "narrativeType": "narrativeGreenery"
            },
            {
              "schemaVersion": "https://movielabs.com/omc/json/schema/v2.6",
              "entityType": "NarrativeObject",
              "identifier": [
                {
                  "identifierScope": "labkoat",
                  "identifierValue": "nprp/CyXsfblZS4UAQJ6SmNn9u"
                }
              ],
              "name": "Red light (Trilobot)",
              "description": "Glowing red light on the head of the Trilobot uses to target its prey.",
              "narrativeType": "narrativeProp"
            },
            {
              "schemaVersion": "https://movielabs.com/omc/json/schema/v2.6",
              "entityType": "NarrativeObject",
              "identifier": [
                {
                  "identifierScope": "labkoat",
                  "identifierValue": "nprp/PAWDCz64zEthoQVVWivOd"
                }
              ],
              "name": "Bush",
              "description": "The bush that Sven tumbles through after the ",
              "narrativeType": "narrativeGreenery"
            },
            {
              "schemaVersion": "https://movielabs.com/omc/json/schema/v2.6",
              "entityType": "NarrativeObject",
              "identifier": [
                {
                  "identifierScope": "labkoat",
                  "identifierValue": "nprp/c7UXpl1eerrigqaZaLTSi"
                }
              ],
              "name": "Tree",
              "description": "The tree that falls on the Trilobot",
              "narrativeType": "narrativeGreenery"
            }
          ],
          "NarrativeStyling": null,
          "SpecialAction": null
        },
        "has": null
      },
      {
        "schemaVersion": "https://movielabs.com/omc/json/schema/v2.6",
        "entityType": "Context",
        "identifier": [
          {
            "identifierScope": "labkoat",
            "identifierValue": "cxt/Ki6uaGlM82HGRlBgEnMXe-2-2"
          }
        ],
        "contextType": "concept",
        "featuresIn": null,
        "needs": null,
        "has": {
          "Asset": [
            {
              "schemaVersion": "https://movielabs.com/omc/json/schema/v2.6",
              "entityType": "Asset",
              "identifier": [
                {
                  "identifierScope": "labkoat",
                  "identifierValue": "asgp/gH1M7UxeR2SYUq7cVyWyB"
                }
              ],
              "name": "Concept Art for Trilobot"
            }
          ]
        }
      }
    ]
  },
  {
    "schemaVersion": "https://movielabs.com/omc/json/schema/v2.6",
    "entityType": "Character",
    "identifier": [
      {
        "identifierScope": "labkoat",
        "identifierValue": "chr/wK6exLR9lnleMcJjc3Ceq"
      }
    ],
    "name": "Juggernaut",
    "Context": [
      {
        "schemaVersion": "https://movielabs.com/omc/json/schema/v2.6",
        "entityType": "Context",
        "identifier": [
          {
            "identifierScope": "labkoat",
            "identifierValue": "cxt/rEbRZuu_BHhsstb48gLw1-1-1"
          }
        ],
        "contextType": "narrative",
        "featuresIn": {
          "NarrativeScene": [
            {
              "schemaVersion": "https://movielabs.com/omc/json/schema/v2.6",
              "entityType": "NarrativeScene",
              "identifier": [
                {
                  "identifierScope": "labkoat",
                  "identifierValue": "nscn/1icPnKZ4LRliFd3WI9urA"
                }
              ],
              "name": "Plateau",
              "description": null,
              "sceneNumber": "7",
              "Context": [
                {
                  "schemaVersion": "https://movielabs.com/omc/json/schema/v2.6",
                  "entityType": "Context",
                  "identifier": [
                    {
                      "identifierScope": "labkoat",
                      "identifierValue": "cxt/xoZa6T_BuGYgHM8Q0rqQt-1-1"
                    }
                  ],
                  "features": {
                    "NarrativeObject": null
                  }
                },
                {
                  "schemaVersion": "https://movielabs.com/omc/json/schema/v2.6",
                  "entityType": "Context",
                  "identifier": [
                    {
                      "identifierScope": "labkoat",
                      "identifierValue": "cxt/xoZa6T_BuGYgHM8Q0rqQt-2-2"
                    }
                  ],
                  "features": {
                    "NarrativeObject": null
                  }
                },
                {
                  "schemaVersion": "https://movielabs.com/omc/json/schema/v2.6",
                  "entityType": "Context",
                  "identifier": [
                    {
                      "identifierScope": "labkoat",
                      "identifierValue": "cxt/xoZa6T_BuGYgHM8Q0rqQt-3-3"
                    }
                  ],
                  "features": {
                    "NarrativeObject": null
                  }
                },
                {
                  "schemaVersion": "https://movielabs.com/omc/json/schema/v2.6",
                  "entityType": "Context",
                  "identifier": [
                    {
                      "identifierScope": "labkoat",
                      "identifierValue": "cxt/xoZa6T_BuGYgHM8Q0rqQt-4-4"
                    }
                  ],
                  "features": {
                    "NarrativeObject": null
                  }
                },
                {
                  "schemaVersion": "https://movielabs.com/omc/json/schema/v2.6",
                  "entityType": "Context",
                  "identifier": [
                    {
                      "identifierScope": "labkoat",
                      "identifierValue": "cxt/xoZa6T_BuGYgHM8Q0rqQt-5-5"
                    }
                  ],
                  "features": {
                    "NarrativeObject": null
                  }
                },
                {
                  "schemaVersion": "https://movielabs.com/omc/json/schema/v2.6",
                  "entityType": "Context",
                  "identifier": [
                    {
                      "identifierScope": "labkoat",
                      "identifierValue": "cxt/xoZa6T_BuGYgHM8Q0rqQt-6-6"
                    }
                  ],
                  "features": {
                    "NarrativeObject": null
                  }
                },
                {
                  "schemaVersion": "https://movielabs.com/omc/json/schema/v2.6",
                  "entityType": "Context",
                  "identifier": [
                    {
                      "identifierScope": "labkoat",
                      "identifierValue": "cxt/xoZa6T_BuGYgHM8Q0rqQt-7-7"
                    }
                  ],
                  "features": {
                    "NarrativeObject": null
                  }
                },
                {
                  "schemaVersion": "https://movielabs.com/omc/json/schema/v2.6",
                  "entityType": "Context",
                  "identifier": [
                    {
                      "identifierScope": "labkoat",
                      "identifierValue": "cxt/xoZa6T_BuGYgHM8Q0rqQt-9-9"
                    }
                  ],
                  "features": null
                },
                {
                  "schemaVersion": "https://movielabs.com/omc/json/schema/v2.6",
                  "entityType": "Context",
                  "identifier": [
                    {
                      "identifierScope": "labkoat",
                      "identifierValue": "cxt/xoZa6T_BuGYgHM8Q0rqQt-10-10"
                    }
                  ],
                  "features": null
                }
              ]
            }
          ]
        },
        "needs": null,
        "has": null
      },
      {
        "schemaVersion": "https://movielabs.com/omc/json/schema/v2.6",
        "entityType": "Context",
        "identifier": [
          {
            "identifierScope": "labkoat",
            "identifierValue": "cxt/rEbRZuu_BHhsstb48gLw1-2-2"
          }
        ],
        "contextType": "concept",
        "featuresIn": null,
        "needs": null,
        "has": {
          "Asset": [
            {
              "schemaVersion": "https://movielabs.com/omc/json/schema/v2.6",
              "entityType": "Asset",
              "identifier": [
                {
                  "identifierScope": "labkoat",
                  "identifierValue": "asgp/H0v_1B2Qc0gSTZ2pM7BSg"
                }
              ],
              "name": "Concept Art for Juggernaut"
            }
          ]
        }
      }
    ]
  },
  {
    "schemaVersion": "https://movielabs.com/omc/json/schema/v2.6",
    "entityType": "Character",
    "identifier": [
      {
        "identifierScope": "labkoat",
        "identifierValue": "chr/HNvHjXqJY9wv1IwjG-Hf1"
      }
    ],
    "name": "Sven",
    "Context": [
      {
        "schemaVersion": "https://movielabs.com/omc/json/schema/v2.6",
        "entityType": "Context",
        "identifier": [
          {
            "identifierScope": "labkoat",
            "identifierValue": "cxt/377RXIREHUj5MPzsl-Sba-1-1"
          }
        ],
        "contextType": "narrative",
        "featuresIn": {
          "NarrativeScene": [
            {
              "schemaVersion": "https://movielabs.com/omc/json/schema/v2.6",
              "entityType": "NarrativeScene",
              "identifier": [
                {
                  "identifierScope": "labkoat",
                  "identifierValue": "nscn/wz_MHOLYI3VwYx_0AX47Y"
                }
              ],
              "name": "Title",
              "description": null,
              "sceneNumber": "1",
              "Context": [
                {
                  "schemaVersion": "https://movielabs.com/omc/json/schema/v2.6",
                  "entityType": "Context",
                  "identifier": [
                    {
                      "identifierScope": "labkoat",
                      "identifierValue": "cxt/Yhk9Nqa9UvkoOmccdPEJf-1-1"
                    }
                  ],
                  "features": {
                    "NarrativeObject": null
                  }
                },
                {
                  "schemaVersion": "https://movielabs.com/omc/json/schema/v2.6",
                  "entityType": "Context",
                  "identifier": [
                    {
                      "identifierScope": "labkoat",
                      "identifierValue": "cxt/Yhk9Nqa9UvkoOmccdPEJf-2-2"
                    }
                  ],
                  "features": {
                    "NarrativeObject": null
                  }
                },
                {
                  "schemaVersion": "https://movielabs.com/omc/json/schema/v2.6",
                  "entityType": "Context",
                  "identifier": [
                    {
                      "identifierScope": "labkoat",
                      "identifierValue": "cxt/Yhk9Nqa9UvkoOmccdPEJf-3-3"
                    }
                  ],
                  "features": {
                    "NarrativeObject": null
                  }
                },
                {
                  "schemaVersion": "https://movielabs.com/omc/json/schema/v2.6",
                  "entityType": "Context",
                  "identifier": [
                    {
                      "identifierScope": "labkoat",
                      "identifierValue": "cxt/Yhk9Nqa9UvkoOmccdPEJf-4-4"
                    }
                  ],
                  "features": {
                    "NarrativeObject": null
                  }
                },
                {
                  "schemaVersion": "https://movielabs.com/omc/json/schema/v2.6",
                  "entityType": "Context",
                  "identifier": [
                    {
                      "identifierScope": "labkoat",
                      "identifierValue": "cxt/Yhk9Nqa9UvkoOmccdPEJf-5-5"
                    }
                  ],
                  "features": null
                },
                {
                  "schemaVersion": "https://movielabs.com/omc/json/schema/v2.6",
                  "entityType": "Context",
                  "identifier": [
                    {
                      "identifierScope": "labkoat",
                      "identifierValue": "cxt/Yhk9Nqa9UvkoOmccdPEJf-6-6"
                    }
                  ],
                  "features": null
                },
                {
                  "schemaVersion": "https://movielabs.com/omc/json/schema/v2.6",
                  "entityType": "Context",
                  "identifier": [
                    {
                      "identifierScope": "labkoat",
                      "identifierValue": "cxt/Yhk9Nqa9UvkoOmccdPEJf-7-7"
                    }
                  ],
                  "features": null
                }
              ]
            },
            {
              "schemaVersion": "https://movielabs.com/omc/json/schema/v2.6",
              "entityType": "NarrativeScene",
              "identifier": [
                {
                  "identifierScope": "labkoat",
                  "identifierValue": "nscn/St_Hh-LxAQo4ICUAtbZ0v"
                }
              ],
              "name": "Space",
              "description": null,
              "sceneNumber": "2",
              "Context": [
                {
                  "schemaVersion": "https://movielabs.com/omc/json/schema/v2.6",
                  "entityType": "Context",
                  "identifier": [
                    {
                      "identifierScope": "labkoat",
                      "identifierValue": "cxt/PyF91eYzluPFglSRgiOdz-1-1"
                    }
                  ],
                  "features": {
                    "NarrativeObject": null
                  }
                },
                {
                  "schemaVersion": "https://movielabs.com/omc/json/schema/v2.6",
                  "entityType": "Context",
                  "identifier": [
                    {
                      "identifierScope": "labkoat",
                      "identifierValue": "cxt/PyF91eYzluPFglSRgiOdz-2-2"
                    }
                  ],
                  "features": {
                    "NarrativeObject": null
                  }
                },
                {
                  "schemaVersion": "https://movielabs.com/omc/json/schema/v2.6",
                  "entityType": "Context",
                  "identifier": [
                    {
                      "identifierScope": "labkoat",
                      "identifierValue": "cxt/PyF91eYzluPFglSRgiOdz-3-3"
                    }
                  ],
                  "features": {
                    "NarrativeObject": null
                  }
                },
                {
                  "schemaVersion": "https://movielabs.com/omc/json/schema/v2.6",
                  "entityType": "Context",
                  "identifier": [
                    {
                      "identifierScope": "labkoat",
                      "identifierValue": "cxt/PyF91eYzluPFglSRgiOdz-4-4"
                    }
                  ],
                  "features": {
                    "NarrativeObject": null
                  }
                },
                {
                  "schemaVersion": "https://movielabs.com/omc/json/schema/v2.6",
                  "entityType": "Context",
                  "identifier": [
                    {
                      "identifierScope": "labkoat",
                      "identifierValue": "cxt/PyF91eYzluPFglSRgiOdz-5-5"
                    }
                  ],
                  "features": null
                },
                {
                  "schemaVersion": "https://movielabs.com/omc/json/schema/v2.6",
                  "entityType": "Context",
                  "identifier": [
                    {
                      "identifierScope": "labkoat",
                      "identifierValue": "cxt/PyF91eYzluPFglSRgiOdz-6-6"
                    }
                  ],
                  "features": null
                },
                {
                  "schemaVersion": "https://movielabs.com/omc/json/schema/v2.6",
                  "entityType": "Context",
                  "identifier": [
                    {
                      "identifierScope": "labkoat",
                      "identifierValue": "cxt/PyF91eYzluPFglSRgiOdz-7-7"
                    }
                  ],
                  "features": null
                }
              ]
            },
            {
              "schemaVersion": "https://movielabs.com/omc/json/schema/v2.6",
              "entityType": "NarrativeScene",
              "identifier": [
                {
                  "identifierScope": "labkoat",
                  "identifierValue": "nscn/xJpXtpM0G2QQM92TITfTf"
                }
              ],
              "name": "Space - Moments Later",
              "description": null,
              "sceneNumber": "3",
              "Context": [
                {
                  "schemaVersion": "https://movielabs.com/omc/json/schema/v2.6",
                  "entityType": "Context",
                  "identifier": [
                    {
                      "identifierScope": "labkoat",
                      "identifierValue": "cxt/dewQzS8jVOgaWkIOSIEwd-1-1"
                    }
                  ],
                  "features": {
                    "NarrativeObject": null
                  }
                },
                {
                  "schemaVersion": "https://movielabs.com/omc/json/schema/v2.6",
                  "entityType": "Context",
                  "identifier": [
                    {
                      "identifierScope": "labkoat",
                      "identifierValue": "cxt/dewQzS8jVOgaWkIOSIEwd-2-2"
                    }
                  ],
                  "features": {
                    "NarrativeObject": null
                  }
                },
                {
                  "schemaVersion": "https://movielabs.com/omc/json/schema/v2.6",
                  "entityType": "Context",
                  "identifier": [
                    {
                      "identifierScope": "labkoat",
                      "identifierValue": "cxt/dewQzS8jVOgaWkIOSIEwd-3-3"
                    }
                  ],
                  "features": {
                    "NarrativeObject": null
                  }
                },
                {
                  "schemaVersion": "https://movielabs.com/omc/json/schema/v2.6",
                  "entityType": "Context",
                  "identifier": [
                    {
                      "identifierScope": "labkoat",
                      "identifierValue": "cxt/dewQzS8jVOgaWkIOSIEwd-4-4"
                    }
                  ],
                  "features": {
                    "NarrativeObject": null
                  }
                },
                {
                  "schemaVersion": "https://movielabs.com/omc/json/schema/v2.6",
                  "entityType": "Context",
                  "identifier": [
                    {
                      "identifierScope": "labkoat",
                      "identifierValue": "cxt/dewQzS8jVOgaWkIOSIEwd-5-5"
                    }
                  ],
                  "features": null
                },
                {
                  "schemaVersion": "https://movielabs.com/omc/json/schema/v2.6",
                  "entityType": "Context",
                  "identifier": [
                    {
                      "identifierScope": "labkoat",
                      "identifierValue": "cxt/dewQzS8jVOgaWkIOSIEwd-6-6"
                    }
                  ],
                  "features": null
                }
              ]
            },
            {
              "schemaVersion": "https://movielabs.com/omc/json/schema/v2.6",
              "entityType": "NarrativeScene",
              "identifier": [
                {
                  "identifierScope": "labkoat",
                  "identifierValue": "nscn/3EF7fR-xOJ7IamLr2iYsg"
                }
              ],
              "name": "Atmosphere",
              "description": null,
              "sceneNumber": "4",
              "Context": [
                {
                  "schemaVersion": "https://movielabs.com/omc/json/schema/v2.6",
                  "entityType": "Context",
                  "identifier": [
                    {
                      "identifierScope": "labkoat",
                      "identifierValue": "cxt/02GT3AlA1wywIJLDIAuUl-1-1"
                    }
                  ],
                  "features": {
                    "NarrativeObject": null
                  }
                },
                {
                  "schemaVersion": "https://movielabs.com/omc/json/schema/v2.6",
                  "entityType": "Context",
                  "identifier": [
                    {
                      "identifierScope": "labkoat",
                      "identifierValue": "cxt/02GT3AlA1wywIJLDIAuUl-2-2"
                    }
                  ],
                  "features": {
                    "NarrativeObject": null
                  }
                },
                {
                  "schemaVersion": "https://movielabs.com/omc/json/schema/v2.6",
                  "entityType": "Context",
                  "identifier": [
                    {
                      "identifierScope": "labkoat",
                      "identifierValue": "cxt/02GT3AlA1wywIJLDIAuUl-3-3"
                    }
                  ],
                  "features": {
                    "NarrativeObject": null
                  }
                },
                {
                  "schemaVersion": "https://movielabs.com/omc/json/schema/v2.6",
                  "entityType": "Context",
                  "identifier": [
                    {
                      "identifierScope": "labkoat",
                      "identifierValue": "cxt/02GT3AlA1wywIJLDIAuUl-4-4"
                    }
                  ],
                  "features": {
                    "NarrativeObject": null
                  }
                },
                {
                  "schemaVersion": "https://movielabs.com/omc/json/schema/v2.6",
                  "entityType": "Context",
                  "identifier": [
                    {
                      "identifierScope": "labkoat",
                      "identifierValue": "cxt/02GT3AlA1wywIJLDIAuUl-6-6"
                    }
                  ],
                  "features": null
                },
                {
                  "schemaVersion": "https://movielabs.com/omc/json/schema/v2.6",
                  "entityType": "Context",
                  "identifier": [
                    {
                      "identifierScope": "labkoat",
                      "identifierValue": "cxt/02GT3AlA1wywIJLDIAuUl-7-7"
                    }
                  ],
                  "features": null
                }
              ]
            },
            {
              "schemaVersion": "https://movielabs.com/omc/json/schema/v2.6",
              "entityType": "NarrativeScene",
              "identifier": [
                {
                  "identifierScope": "labkoat",
                  "identifierValue": "nscn/lmPkGo1nXjJgfeNnoxArq"
                }
              ],
              "name": "Beach",
              "description": null,
              "sceneNumber": "5",
              "Context": [
                {
                  "schemaVersion": "https://movielabs.com/omc/json/schema/v2.6",
                  "entityType": "Context",
                  "identifier": [
                    {
                      "identifierScope": "labkoat",
                      "identifierValue": "cxt/qywm_qU78IVRhQtagirto-1-1"
                    }
                  ],
                  "features": {
                    "NarrativeObject": null
                  }
                },
                {
                  "schemaVersion": "https://movielabs.com/omc/json/schema/v2.6",
                  "entityType": "Context",
                  "identifier": [
                    {
                      "identifierScope": "labkoat",
                      "identifierValue": "cxt/qywm_qU78IVRhQtagirto-2-2"
                    }
                  ],
                  "features": {
                    "NarrativeObject": null
                  }
                },
                {
                  "schemaVersion": "https://movielabs.com/omc/json/schema/v2.6",
                  "entityType": "Context",
                  "identifier": [
                    {
                      "identifierScope": "labkoat",
                      "identifierValue": "cxt/qywm_qU78IVRhQtagirto-3-3"
                    }
                  ],
                  "features": {
                    "NarrativeObject": null
                  }
                },
                {
                  "schemaVersion": "https://movielabs.com/omc/json/schema/v2.6",
                  "entityType": "Context",
                  "identifier": [
                    {
                      "identifierScope": "labkoat",
                      "identifierValue": "cxt/qywm_qU78IVRhQtagirto-4-4"
                    }
                  ],
                  "features": {
                    "NarrativeObject": null
                  }
                },
                {
                  "schemaVersion": "https://movielabs.com/omc/json/schema/v2.6",
                  "entityType": "Context",
                  "identifier": [
                    {
                      "identifierScope": "labkoat",
                      "identifierValue": "cxt/qywm_qU78IVRhQtagirto-5-5"
                    }
                  ],
                  "features": {
                    "NarrativeObject": null
                  }
                },
                {
                  "schemaVersion": "https://movielabs.com/omc/json/schema/v2.6",
                  "entityType": "Context",
                  "identifier": [
                    {
                      "identifierScope": "labkoat",
                      "identifierValue": "cxt/qywm_qU78IVRhQtagirto-7-7"
                    }
                  ],
                  "features": null
                },
                {
                  "schemaVersion": "https://movielabs.com/omc/json/schema/v2.6",
                  "entityType": "Context",
                  "identifier": [
                    {
                      "identifierScope": "labkoat",
                      "identifierValue": "cxt/qywm_qU78IVRhQtagirto-8-8"
                    }
                  ],
                  "features": null
                }
              ]
            },
            {
              "schemaVersion": "https://movielabs.com/omc/json/schema/v2.6",
              "entityType": "NarrativeScene",
              "identifier": [
                {
                  "identifierScope": "labkoat",
                  "identifierValue": "nscn/zH9BzX8cjf-wY6N-HE6fg"
                }
              ],
              "name": "Jungle",
              "description": null,
              "sceneNumber": "6",
              "Context": [
                {
                  "schemaVersion": "https://movielabs.com/omc/json/schema/v2.6",
                  "entityType": "Context",
                  "identifier": [
                    {
                      "identifierScope": "labkoat",
                      "identifierValue": "cxt/G2_QEXSZYS32wc3Z0Ecdx-1-1"
                    }
                  ],
                  "features": {
                    "NarrativeObject": null
                  }
                },
                {
                  "schemaVersion": "https://movielabs.com/omc/json/schema/v2.6",
                  "entityType": "Context",
                  "identifier": [
                    {
                      "identifierScope": "labkoat",
                      "identifierValue": "cxt/G2_QEXSZYS32wc3Z0Ecdx-2-2"
                    }
                  ],
                  "features": {
                    "NarrativeObject": null
                  }
                },
                {
                  "schemaVersion": "https://movielabs.com/omc/json/schema/v2.6",
                  "entityType": "Context",
                  "identifier": [
                    {
                      "identifierScope": "labkoat",
                      "identifierValue": "cxt/G2_QEXSZYS32wc3Z0Ecdx-3-3"
                    }
                  ],
                  "features": {
                    "NarrativeObject": null
                  }
                },
                {
                  "schemaVersion": "https://movielabs.com/omc/json/schema/v2.6",
                  "entityType": "Context",
                  "identifier": [
                    {
                      "identifierScope": "labkoat",
                      "identifierValue": "cxt/G2_QEXSZYS32wc3Z0Ecdx-4-4"
                    }
                  ],
                  "features": {
                    "NarrativeObject": null
                  }
                },
                {
                  "schemaVersion": "https://movielabs.com/omc/json/schema/v2.6",
                  "entityType": "Context",
                  "identifier": [
                    {
                      "identifierScope": "labkoat",
                      "identifierValue": "cxt/G2_QEXSZYS32wc3Z0Ecdx-6-6"
                    }
                  ],
                  "features": null
                },
                {
                  "schemaVersion": "https://movielabs.com/omc/json/schema/v2.6",
                  "entityType": "Context",
                  "identifier": [
                    {
                      "identifierScope": "labkoat",
                      "identifierValue": "cxt/G2_QEXSZYS32wc3Z0Ecdx-7-7"
                    }
                  ],
                  "features": null
                }
              ]
            },
            {
              "schemaVersion": "https://movielabs.com/omc/json/schema/v2.6",
              "entityType": "NarrativeScene",
              "identifier": [
                {
                  "identifierScope": "labkoat",
                  "identifierValue": "nscn/1icPnKZ4LRliFd3WI9urA"
                }
              ],
              "name": "Plateau",
              "description": null,
              "sceneNumber": "7",
              "Context": [
                {
                  "schemaVersion": "https://movielabs.com/omc/json/schema/v2.6",
                  "entityType": "Context",
                  "identifier": [
                    {
                      "identifierScope": "labkoat",
                      "identifierValue": "cxt/xoZa6T_BuGYgHM8Q0rqQt-1-1"
                    }
                  ],
                  "features": {
                    "NarrativeObject": null
                  }
                },
                {
                  "schemaVersion": "https://movielabs.com/omc/json/schema/v2.6",
                  "entityType": "Context",
                  "identifier": [
                    {
                      "identifierScope": "labkoat",
                      "identifierValue": "cxt/xoZa6T_BuGYgHM8Q0rqQt-2-2"
                    }
                  ],
                  "features": {
                    "NarrativeObject": null
                  }
                },
                {
                  "schemaVersion": "https://movielabs.com/omc/json/schema/v2.6",
                  "entityType": "Context",
                  "identifier": [
                    {
                      "identifierScope": "labkoat",
                      "identifierValue": "cxt/xoZa6T_BuGYgHM8Q0rqQt-3-3"
                    }
                  ],
                  "features": {
                    "NarrativeObject": null
                  }
                },
                {
                  "schemaVersion": "https://movielabs.com/omc/json/schema/v2.6",
                  "entityType": "Context",
                  "identifier": [
                    {
                      "identifierScope": "labkoat",
                      "identifierValue": "cxt/xoZa6T_BuGYgHM8Q0rqQt-4-4"
                    }
                  ],
                  "features": {
                    "NarrativeObject": null
                  }
                },
                {
                  "schemaVersion": "https://movielabs.com/omc/json/schema/v2.6",
                  "entityType": "Context",
                  "identifier": [
                    {
                      "identifierScope": "labkoat",
                      "identifierValue": "cxt/xoZa6T_BuGYgHM8Q0rqQt-5-5"
                    }
                  ],
                  "features": {
                    "NarrativeObject": null
                  }
                },
                {
                  "schemaVersion": "https://movielabs.com/omc/json/schema/v2.6",
                  "entityType": "Context",
                  "identifier": [
                    {
                      "identifierScope": "labkoat",
                      "identifierValue": "cxt/xoZa6T_BuGYgHM8Q0rqQt-6-6"
                    }
                  ],
                  "features": {
                    "NarrativeObject": null
                  }
                },
                {
                  "schemaVersion": "https://movielabs.com/omc/json/schema/v2.6",
                  "entityType": "Context",
                  "identifier": [
                    {
                      "identifierScope": "labkoat",
                      "identifierValue": "cxt/xoZa6T_BuGYgHM8Q0rqQt-7-7"
                    }
                  ],
                  "features": {
                    "NarrativeObject": null
                  }
                },
                {
                  "schemaVersion": "https://movielabs.com/omc/json/schema/v2.6",
                  "entityType": "Context",
                  "identifier": [
                    {
                      "identifierScope": "labkoat",
                      "identifierValue": "cxt/xoZa6T_BuGYgHM8Q0rqQt-9-9"
                    }
                  ],
                  "features": null
                },
                {
                  "schemaVersion": "https://movielabs.com/omc/json/schema/v2.6",
                  "entityType": "Context",
                  "identifier": [
                    {
                      "identifierScope": "labkoat",
                      "identifierValue": "cxt/xoZa6T_BuGYgHM8Q0rqQt-10-10"
                    }
                  ],
                  "features": null
                }
              ]
            }
          ]
        },
        "needs": {
          "NarrativeObject": [
            {
              "schemaVersion": "https://movielabs.com/omc/json/schema/v2.6",
              "entityType": "NarrativeObject",
              "identifier": [
                {
                  "identifierScope": "labkoat",
                  "identifierValue": "nprp/4ADqu_vf7ji85PLYOott1"
                }
              ],
              "name": "Wreckage",
              "description": "The wreckage of Sven's ship after it hits the water.",
              "narrativeType": "narrativeProp"
            },
            {
              "schemaVersion": "https://movielabs.com/omc/json/schema/v2.6",
              "entityType": "NarrativeObject",
              "identifier": [
                {
                  "identifierScope": "labkoat",
                  "identifierValue": "nprp/ozmg19-jNdhIlO1HwVP5G"
                }
              ],
              "name": "Satellites hatch",
              "description": "The hatch Sven removes to fix the satellite.",
              "narrativeType": "narrativeProp"
            },
            {
              "schemaVersion": "https://movielabs.com/omc/json/schema/v2.6",
              "entityType": "NarrativeObject",
              "identifier": [
                {
                  "identifierScope": "labkoat",
                  "identifierValue": "nprp/aAZTJ26A0mCCLosGQ3Ryg"
                }
              ],
              "name": "Windshield",
              "description": "The windshield of Sven's ship.",
              "narrativeType": "narrativeProp"
            },
            {
              "schemaVersion": "https://movielabs.com/omc/json/schema/v2.6",
              "entityType": "NarrativeObject",
              "identifier": [
                {
                  "identifierScope": "labkoat",
                  "identifierValue": "nprp/YESjEAVPVMJL2edrroe2o"
                }
              ],
              "name": "Panel",
              "description": "The panel inside the satellite where Sven finds the sabotaged wires.",
              "narrativeType": "narrativeProp"
            },
            {
              "schemaVersion": "https://movielabs.com/omc/json/schema/v2.6",
              "entityType": "NarrativeObject",
              "identifier": [
                {
                  "identifierScope": "labkoat",
                  "identifierValue": "nprp/jpiWPupPSRvHyAiUSyn0_"
                }
              ],
              "name": "Switch",
              "description": "The switch inside the panel Sven uses to turn on the satellite.",
              "narrativeType": "narrativeProp"
            },
            {
              "schemaVersion": "https://movielabs.com/omc/json/schema/v2.6",
              "entityType": "NarrativeObject",
              "identifier": [
                {
                  "identifierScope": "labkoat",
                  "identifierValue": "nprp/9ezqw5mMlPLoloD86u6aI"
                }
              ],
              "name": "Jetpack",
              "description": "Sven's Orion-9 jet pack he uses to move around usually only used in space.",
              "narrativeType": "narrativeProp"
            },
            {
              "schemaVersion": "https://movielabs.com/omc/json/schema/v2.6",
              "entityType": "NarrativeObject",
              "identifier": [
                {
                  "identifierScope": "labkoat",
                  "identifierValue": "nprp/5is74zVxCRl5hipIHfMzB"
                }
              ],
              "name": "Satellite",
              "description": "The Gromet-12 plantetary observation satellite finds planets that are habitable for humans",
              "narrativeType": "narrativeProp"
            },
            {
              "schemaVersion": "https://movielabs.com/omc/json/schema/v2.6",
              "entityType": "NarrativeObject",
              "identifier": [
                {
                  "identifierScope": "labkoat",
                  "identifierValue": "nprp/vgGK6PF2s1FGziyehshia"
                }
              ],
              "name": "Broken pipes",
              "description": "The pipes inside the satellite that are broken",
              "narrativeType": "narrativeProp"
            },
            {
              "schemaVersion": "https://movielabs.com/omc/json/schema/v2.6",
              "entityType": "NarrativeObject",
              "identifier": [
                {
                  "identifierScope": "labkoat",
                  "identifierValue": "nprp/cqDBPztY_8fCs3mjU2Tq9"
                }
              ],
              "name": "Eject button",
              "description": "The button Sven pushes to eject from the Lancelot-12 galaxy cruiser",
              "narrativeType": "narrativeProp"
            },
            {
              "schemaVersion": "https://movielabs.com/omc/json/schema/v2.6",
              "entityType": "NarrativeObject",
              "identifier": [
                {
                  "identifierScope": "labkoat",
                  "identifierValue": "nprp/R7wfwv6cSPc6d1t1_glgJ"
                }
              ],
              "name": "Communicator",
              "description": "The Mark-14 Intergalactic communicator allows Sven to connect with Central Command. ",
              "narrativeType": "narrativeProp"
            },
            {
              "schemaVersion": "https://movielabs.com/omc/json/schema/v2.6",
              "entityType": "NarrativeObject",
              "identifier": [
                {
                  "identifierScope": "labkoat",
                  "identifierValue": "nprp/Lp5AP7ZQiwfRpeB_qIrXf"
                }
              ],
              "name": "Fruit",
              "description": "The exploding fruit found in the jungle.",
              "narrativeType": "narrativeProp"
            },
            {
              "schemaVersion": "https://movielabs.com/omc/json/schema/v2.6",
              "entityType": "NarrativeObject",
              "identifier": [
                {
                  "identifierScope": "labkoat",
                  "identifierValue": "nprp/zVJeW6nTeg8PKVJ_F0t5C"
                }
              ],
              "name": "Welder",
              "description": "The Prime-94 arc welder is as hot as the sun and can cut through most known metals.",
              "narrativeType": "narrativeProp"
            },
            {
              "schemaVersion": "https://movielabs.com/omc/json/schema/v2.6",
              "entityType": "NarrativeObject",
              "identifier": [
                {
                  "identifierScope": "labkoat",
                  "identifierValue": "nprp/eM2Njo6EK-OEIzEL9xDlr"
                }
              ],
              "name": "Fruit cluster",
              "description": "The cluster of fruit Sven sets off to kill the Trilobot",
              "narrativeType": "narrativeProp"
            },
            {
              "schemaVersion": "https://movielabs.com/omc/json/schema/v2.6",
              "entityType": "NarrativeObject",
              "identifier": [
                {
                  "identifierScope": "labkoat",
                  "identifierValue": "nprp/PFYNfswZXdTqm1l62DfSr"
                }
              ],
              "name": "Disconnected wires",
              "description": "The disconnected wires in the satellite panel Sven has to fix.",
              "narrativeType": "narrativeProp"
            },
            {
              "schemaVersion": "https://movielabs.com/omc/json/schema/v2.6",
              "entityType": "NarrativeObject",
              "identifier": [
                {
                  "identifierScope": "labkoat",
                  "identifierValue": "nprp/BtBYAFQ_Moo4PQlqSztGz"
                }
              ],
              "name": "Rock - Beach",
              "description": "The rock on the beach that Sven hides behind.",
              "narrativeType": "narrativeProp"
            },
            {
              "schemaVersion": "https://movielabs.com/omc/json/schema/v2.6",
              "entityType": "NarrativeObject",
              "identifier": [
                {
                  "identifierScope": "labkoat",
                  "identifierValue": "nprp/XkxEwUpJGpxExmXj6FBv_"
                }
              ],
              "name": "Wrench",
              "description": "The Prime-97 electric wrench  is the swiss army knife of repair tools for Sven",
              "narrativeType": "narrativeProp"
            },
            {
              "schemaVersion": "https://movielabs.com/omc/json/schema/v2.6",
              "entityType": "NarrativeObject",
              "identifier": [
                {
                  "identifierScope": "labkoat",
                  "identifierValue": "nprp/ryhQTqM7Dpo0fe-9PJhQh"
                }
              ],
              "name": "Spaceship",
              "description": "Sven's Lancelot-12 galaxy cruiser which is the pick up truck of space vehicles",
              "narrativeType": "narrativeVehicle"
            },
            {
              "schemaVersion": "https://movielabs.com/omc/json/schema/v2.6",
              "entityType": "NarrativeObject",
              "identifier": [
                {
                  "identifierScope": "labkoat",
                  "identifierValue": "nprp/HL9EpbbzFK320fweoiFsM"
                }
              ],
              "name": "Ground",
              "description": "The terrain that Sven runs on in the Jungle and Plateau",
              "narrativeType": "narrativeGreenery"
            },
            {
              "schemaVersion": "https://movielabs.com/omc/json/schema/v2.6",
              "entityType": "NarrativeObject",
              "identifier": [
                {
                  "identifierScope": "labkoat",
                  "identifierValue": "nprp/OAjeFuQtL5Au4DHJMu6Uz"
                }
              ],
              "name": "Canopy",
              "description": "The canopy that Svens breaks through as he runs through the jungle.",
              "narrativeType": "narrativeGreenery"
            },
            {
              "schemaVersion": "https://movielabs.com/omc/json/schema/v2.6",
              "entityType": "NarrativeObject",
              "identifier": [
                {
                  "identifierScope": "labkoat",
                  "identifierValue": "nprp/PAWDCz64zEthoQVVWivOd"
                }
              ],
              "name": "Bush",
              "description": "The bush that Sven tumbles through after the ",
              "narrativeType": "narrativeGreenery"
            },
            {
              "schemaVersion": "https://movielabs.com/omc/json/schema/v2.6",
              "entityType": "NarrativeObject",
              "identifier": [
                {
                  "identifierScope": "labkoat",
                  "identifierValue": "nprp/nsLRumyU2pd_7DPTFCpoj"
                }
              ],
              "name": "Spaceship Chair",
              "description": "The chair that Sven uses to eject from the spaceship.",
              "narrativeType": "narrativeProp"
            },
            {
              "schemaVersion": "https://movielabs.com/omc/json/schema/v2.6",
              "entityType": "NarrativeObject",
              "identifier": [
                {
                  "identifierScope": "labkoat",
                  "identifierValue": "nprp/c7UXpl1eerrigqaZaLTSi"
                }
              ],
              "name": "Tree",
              "description": "The tree that falls on the Trilobot",
              "narrativeType": "narrativeGreenery"
            },
            {
              "schemaVersion": "https://movielabs.com/omc/json/schema/v2.6",
              "entityType": "NarrativeObject",
              "identifier": [
                {
                  "identifierScope": "labkoat",
                  "identifierValue": "nprp/psNDy6gpu-aVkc79Jdb0c"
                }
              ],
              "name": "Helmet",
              "description": "The helmet to Sven's spacesuit.",
              "narrativeType": "narrativeProp"
            }
          ],
          "NarrativeStyling": null,
          "SpecialAction": null
        },
        "has": null
      },
      {
        "schemaVersion": "https://movielabs.com/omc/json/schema/v2.6",
        "entityType": "Context",
        "identifier": [
          {
            "identifierScope": "labkoat",
            "identifierValue": "cxt/377RXIREHUj5MPzsl-Sba-2-2"
          }
        ],
        "contextType": "concept",
        "featuresIn": null,
        "needs": null,
        "has": {
          "Asset": [
            {
              "schemaVersion": "https://movielabs.com/omc/json/schema/v2.6",
              "entityType": "Asset",
              "identifier": [
                {
                  "identifierScope": "labkoat",
                  "identifierValue": "asgp/6ijmAYmCMY86OQtX4cZ_y"
                }
              ],
              "name": "Concept Art for Sven"
            }
          ]
        }
      }
    ]
  },
  {
    "schemaVersion": "https://movielabs.com/omc/json/schema/v2.6",
    "entityType": "Character",
    "identifier": [
      {
        "identifierScope": "labkoat",
        "identifierValue": "chr/LC4nrtxXR3CVPDUr8DAOJ"
      }
    ],
    "name": "Killimari",
    "Context": [
      {
        "schemaVersion": "https://movielabs.com/omc/json/schema/v2.6",
        "entityType": "Context",
        "identifier": [
          {
            "identifierScope": "labkoat",
            "identifierValue": "cxt/NpYI-Tkz81bEJCmyAAbql-1-1"
          }
        ],
        "contextType": "narrative",
        "featuresIn": {
          "NarrativeScene": [
            {
              "schemaVersion": "https://movielabs.com/omc/json/schema/v2.6",
              "entityType": "NarrativeScene",
              "identifier": [
                {
                  "identifierScope": "labkoat",
                  "identifierValue": "nscn/1icPnKZ4LRliFd3WI9urA"
                }
              ],
              "name": "Plateau",
              "description": null,
              "sceneNumber": "7",
              "Context": [
                {
                  "schemaVersion": "https://movielabs.com/omc/json/schema/v2.6",
                  "entityType": "Context",
                  "identifier": [
                    {
                      "identifierScope": "labkoat",
                      "identifierValue": "cxt/xoZa6T_BuGYgHM8Q0rqQt-1-1"
                    }
                  ],
                  "features": {
                    "NarrativeObject": null
                  }
                },
                {
                  "schemaVersion": "https://movielabs.com/omc/json/schema/v2.6",
                  "entityType": "Context",
                  "identifier": [
                    {
                      "identifierScope": "labkoat",
                      "identifierValue": "cxt/xoZa6T_BuGYgHM8Q0rqQt-2-2"
                    }
                  ],
                  "features": {
                    "NarrativeObject": null
                  }
                },
                {
                  "schemaVersion": "https://movielabs.com/omc/json/schema/v2.6",
                  "entityType": "Context",
                  "identifier": [
                    {
                      "identifierScope": "labkoat",
                      "identifierValue": "cxt/xoZa6T_BuGYgHM8Q0rqQt-3-3"
                    }
                  ],
                  "features": {
                    "NarrativeObject": null
                  }
                },
                {
                  "schemaVersion": "https://movielabs.com/omc/json/schema/v2.6",
                  "entityType": "Context",
                  "identifier": [
                    {
                      "identifierScope": "labkoat",
                      "identifierValue": "cxt/xoZa6T_BuGYgHM8Q0rqQt-4-4"
                    }
                  ],
                  "features": {
                    "NarrativeObject": null
                  }
                },
                {
                  "schemaVersion": "https://movielabs.com/omc/json/schema/v2.6",
                  "entityType": "Context",
                  "identifier": [
                    {
                      "identifierScope": "labkoat",
                      "identifierValue": "cxt/xoZa6T_BuGYgHM8Q0rqQt-5-5"
                    }
                  ],
                  "features": {
                    "NarrativeObject": null
                  }
                },
                {
                  "schemaVersion": "https://movielabs.com/omc/json/schema/v2.6",
                  "entityType": "Context",
                  "identifier": [
                    {
                      "identifierScope": "labkoat",
                      "identifierValue": "cxt/xoZa6T_BuGYgHM8Q0rqQt-6-6"
                    }
                  ],
                  "features": {
                    "NarrativeObject": null
                  }
                },
                {
                  "schemaVersion": "https://movielabs.com/omc/json/schema/v2.6",
                  "entityType": "Context",
                  "identifier": [
                    {
                      "identifierScope": "labkoat",
                      "identifierValue": "cxt/xoZa6T_BuGYgHM8Q0rqQt-7-7"
                    }
                  ],
                  "features": {
                    "NarrativeObject": null
                  }
                },
                {
                  "schemaVersion": "https://movielabs.com/omc/json/schema/v2.6",
                  "entityType": "Context",
                  "identifier": [
                    {
                      "identifierScope": "labkoat",
                      "identifierValue": "cxt/xoZa6T_BuGYgHM8Q0rqQt-9-9"
                    }
                  ],
                  "features": null
                },
                {
                  "schemaVersion": "https://movielabs.com/omc/json/schema/v2.6",
                  "entityType": "Context",
                  "identifier": [
                    {
                      "identifierScope": "labkoat",
                      "identifierValue": "cxt/xoZa6T_BuGYgHM8Q0rqQt-10-10"
                    }
                  ],
                  "features": null
                }
              ]
            }
          ]
        },
        "needs": null,
        "has": null
      },
      {
        "schemaVersion": "https://movielabs.com/omc/json/schema/v2.6",
        "entityType": "Context",
        "identifier": [
          {
            "identifierScope": "labkoat",
            "identifierValue": "cxt/NpYI-Tkz81bEJCmyAAbql-2-2"
          }
        ],
        "contextType": "concept",
        "featuresIn": null,
        "needs": null,
        "has": {
          "Asset": [
            {
              "schemaVersion": "https://movielabs.com/omc/json/schema/v2.6",
              "entityType": "Asset",
              "identifier": [
                {
                  "identifierScope": "labkoat",
                  "identifierValue": "asgp/t5D9BlW8Dsh3Le2174gni"
                }
              ],
              "name": "Concept Art for Kilimari"
            }
          ]
        }
      }
    ]
  }
]
